setup.cfg
setup.py
cadc/__init__.py
cadc/__version__.py
cadc.egg-info/PKG-INFO
cadc.egg-info/SOURCES.txt
cadc.egg-info/dependency_links.txt
cadc.egg-info/not-zip-safe
cadc.egg-info/pbr.json
cadc.egg-info/requires.txt
cadc.egg-info/top_level.txt
cadc/data/__init__.py
cadc/data/client.py
cadc/data/constants.py
cadc/data/exceptions.py
cadc/data/protocol.py
cadc/data/transfer.py
cadc/data/transfer_reader.py
cadc/data/transfer_writer.py
scripts/cadc-copy
scripts/cadc-fileinfo