Metadata-Version: 1.1
Name: cadc
Version: 0.2.2
Summary: Python client libraries and scripts for CADC web services
Home-page: https://github.com/canfar/python-canfar-clients
Author: Ed Chapin, Jeff Burke, Dustin Jenkins
Author-email: cadc@nrc.ca
License: GNU Affero General Public License v3.0
Platform: UNKNOWN
Provides: cadc
